instadump/__init__.py
instadump/cli/__init__.py
instadump/cli/crawl.py
instadump/cli/download.py
instadump/lib/__init__.py
instadump/lib/config.py
instadump/lib/downloader.py
instadump/lib/instagram.py
instadump/lib/utils.py
instadump-0.2.1.dist-info/METADATA
instadump-0.2.1.dist-info/WHEEL
instadump-0.2.1.dist-info/entry_points.txt
instadump-0.2.1.dist-info/RECORD
