Metadata-Version: 2.1
Name: instadump
Version: 0.2.1
Summary: 
Author: redraw
Author-email: redraw@sdf.org
Requires-Python: >=3.10,<4.0
Classifier: Programming Language :: Python :: 3
Classifier: Programming Language :: Python :: 3.10
Classifier: Programming Language :: Python :: 3.11
Requires-Dist: aiofiles (>=23.2.1,<24.0.0)
Requires-Dist: httpx (>=0.25.0,<0.26.0)
Requires-Dist: python-dateutil (>=2.8.2,<3.0.0)
Requires-Dist: pyyaml (>=6.0.1,<7.0.0)
Requires-Dist: tqdm (>=4.66.1,<5.0.0)
Requires-Dist: typer (>=0.9.0,<0.10.0)
